LICENSE
MANIFEST.in
README.md
pyproject.toml
setup.py
pdwt/src/common.cu
pdwt/src/common.h
pdwt/src/filters.cpp
pdwt/src/filters.h
pdwt/src/haar.cu
pdwt/src/haar.h
pdwt/src/io.h
pdwt/src/nonseparable.cu
pdwt/src/nonseparable.h
pdwt/src/separable.cu
pdwt/src/separable.h
pdwt/src/utils.cu
pdwt/src/utils.h
pdwt/src/wt.cu
pdwt/src/wt.h
pycudwt_multitarget.egg-info/PKG-INFO
pycudwt_multitarget.egg-info/SOURCES.txt
pycudwt_multitarget.egg-info/dependency_links.txt
pycudwt_multitarget.egg-info/not-zip-safe
pycudwt_multitarget.egg-info/requires.txt
pycudwt_multitarget.egg-info/top_level.txt
src/pypwt.pyx
test/test_all.py
test/test_single.py
test/test_sizes.py
test/test_wavelets.py
test/testutils.py