Metadata-Version: 2.1
Name: pycudwt-multitarget
Version: 1.0.5
Author: Pierre Paleo
Author-email: pierre.paleo@esrf.fr
Maintainer: Will Drevo
Maintainer-email: will.drevo@gmail.com
License-File: LICENSE
